pkrhistorysplitter/__init__.py
pkrhistorysplitter/app.py
pkrhistorysplitter/downloader.py
pkrhistorysplitter/splitter.py
pkrhistorysplitter/watch_bucket.py
pkrhistorysplitter/watchdog.py
pkrhistorysplitter-1.0.1.dist-info/METADATA
pkrhistorysplitter-1.0.1.dist-info/WHEEL
pkrhistorysplitter-1.0.1.dist-info/top_level.txt
pkrhistorysplitter-1.0.1.dist-info/RECORD
