Metadata-Version: 2.1
Name: pkrhistorysplitter
Version: 1.0.1
Summary: A Poker Package to split poker history files in DO S3 bucket
Home-page: https://github.com/manggy94/PokerHistorySplitter
Author: Alexandre MANGWA
Author-email: alex.mangwa@gmail.com
License: UNKNOWN
Keywords: poker pkrhistory history pkr pkrhistorysplitter pokerhistory splitter downloader
Platform: UNKNOWN
Classifier: Development Status :: 4 - Beta
Classifier: Intended Audience :: Developers
Classifier: License :: OSI Approved :: MIT License
Classifier: Natural Language :: English
Classifier: Natural Language :: French
Classifier: Programming Language :: Python
Classifier: Programming Language :: Python :: 3
Classifier: Topic :: Games/Entertainment
Classifier: Topic :: Games/Entertainment :: Board Games
Requires-Dist: boto3
Requires-Dist: python-dotenv
